latexgenlib/__init__.py
latexgenlib/latex_generator.py
latexgenlib-0.1.1.dist-info/METADATA
latexgenlib-0.1.1.dist-info/WHEEL
latexgenlib-0.1.1.dist-info/top_level.txt
latexgenlib-0.1.1.dist-info/RECORD
